{
  "project_info": {
    "project_number": "327214522186",
    "project_id": "flavor-a3582",
    "storage_bucket": "flavor-a3582.appspot.com"
  },
  "client": [
    {
      "client_info": {
        "mobilesdk_app_id": "1:327214522186:android:adba5129284cfa4a89abb3",
        "android_client_info": {
          "package_name": "com.example.flavorDev"
        }
      },
      "oauth_client": [],
      "api_key": [
        {
          "current_key": "AIzaSyDFSdktJrpQUlfpajW8wYwwfTNmuPlCeWQ"
        }
      ],
      "services": {
        "appinvite_service": {
          "other_platform_oauth_client": []
        }
      }
    },
    {
      "client_info": {
        "mobilesdk_app_id": "1:327214522186:android:c1f46cdcaab0935089abb3",
        "android_client_info": {
          "package_name": "com.example.flavorProd"
        }
      },
      "oauth_client": [],
      "api_key": [
        {
          "current_key": "AIzaSyDFSdktJrpQUlfpajW8wYwwfTNmuPlCeWQ"
        }
      ],
      "services": {
        "appinvite_service": {
          "other_platform_oauth_client": []
        }
      }
    },
    {
      "client_info": {
        "mobilesdk_app_id": "1:327214522186:android:1ffde2e743c0d65789abb3",
        "android_client_info": {
          "package_name": "com.example.flavorStage"
        }
      },
      "oauth_client": [],
      "api_key": [
        {
          "current_key": "AIzaSyDFSdktJrpQUlfpajW8wYwwfTNmuPlCeWQ"
        }
      ],
      "services": {
        "appinvite_service": {
          "other_platform_oauth_client": []
        }
      }
    },
    {
      "client_info": {
        "mobilesdk_app_id": "1:327214522186:android:d4ef252eea14ed5d89abb3",
        "android_client_info": {
          "package_name": "com.example.flavorTest"
        }
      },
      "oauth_client": [],
      "api_key": [
        {
          "current_key": "AIzaSyDFSdktJrpQUlfpajW8wYwwfTNmuPlCeWQ"
        }
      ],
      "services": {
        "appinvite_service": {
          "other_platform_oauth_client": []
        }
      }
    }
  ],
  "configuration_version": "1"
}
